zxcdsaweercvvv/__init__.py
zxcdsaweercvvv/demo1.py
zxcdsaweercvvv/demo2.py
zxcdsaweercvvv-1.0.dist-info/METADATA
zxcdsaweercvvv-1.0.dist-info/WHEEL
zxcdsaweercvvv-1.0.dist-info/top_level.txt
zxcdsaweercvvv-1.0.dist-info/RECORD
