Metadata-Version: 2.1
Name: zxcdsaweercvvv
Version: 1.0
Summary: 这是第一个对外发布的模块，测试哦
Author: gaoqi
Author-email: 213@163.com
